unravel_client/__init__.py
unravel_client/constants.py
unravel_client/decorators.py
unravel_client/price.py
unravel_client/portfolio/__init__.py
unravel_client/portfolio/factors.py
unravel_client/portfolio/historical_weights.py
unravel_client/portfolio/live_weights.py
unravel_client/portfolio/returns.py
unravel_client/portfolio/risk.py
unravel_client/portfolio/tickers.py
unravel_client/portfolio/universe.py
unravel_client-3.0.0.dist-info/METADATA
unravel_client-3.0.0.dist-info/WHEEL
unravel_client-3.0.0.dist-info/licenses/LICENSE
unravel_client-3.0.0.dist-info/RECORD
