Metadata-Version: 2.4
Name: unravel-client
Version: 3.0.0
Summary: Client API for unravel.finance, multi-factor, market-neutral crypto portfolios and cross-sectional factors
Project-URL: Issues, https://github.com/unravel-finance/unravel-client/issues
Project-URL: Source, https://github.com/unravel-finance/unravel-client
Author-email: Mark Aron Szulyovszky <mark@unravel.finance>, Daniel Szemerey <daniel@unravel.finance>
License-Expression: MIT
License-File: LICENSE
Keywords: api,backtesting,market-neutral,portfolio,quant,quantiative,risk
Classifier: Development Status :: 5 - Production/Stable
Classifier: License :: Other/Proprietary License
Classifier: Operating System :: OS Independent
Classifier: Programming Language :: Python
Classifier: Programming Language :: Python :: 3.11
Classifier: Programming Language :: Python :: Implementation :: CPython
Classifier: Programming Language :: Python :: Implementation :: PyPy
Requires-Python: >=3.11
Requires-Dist: numpy>=1.3.0
Requires-Dist: pandas>=2.0.0
Requires-Dist: requests>=2.25.0
Requires-Dist: tqdm>=4.66.4
Provides-Extra: quality
Requires-Dist: pre-commit~=2.20.0; extra == 'quality'
Requires-Dist: ruff==0.1.11; extra == 'quality'
Provides-Extra: tests
Requires-Dist: hypothesis~=6.112.4; extra == 'tests'
Requires-Dist: pytest-cov>=4.0; extra == 'tests'
Requires-Dist: pytest~=7.1.2; extra == 'tests'
Requires-Dist: python-dotenv>=1.0.0; extra == 'tests'
